propensitybatchrandomization/__init__.py
propensitybatchrandomization/propensityScore.py
propensitybatchrandomization/randomAssignment.py
propensitybatchrandomization-0.1.0.dist-info/METADATA
propensitybatchrandomization-0.1.0.dist-info/WHEEL
propensitybatchrandomization-0.1.0.dist-info/RECORD
