Metadata-Version: 2.4
Name: propensitybatchrandomization
Version: 0.1.0
Summary: A tool for randomizing biological samples across batches while maintaining covariate balance through propensity score–based evaluation.
License: MIT
Author: Mathew Wingerson
Requires-Python: >=3.12
Classifier: License :: OSI Approved :: MIT License
Classifier: Programming Language :: Python :: 3
Classifier: Programming Language :: Python :: 3.12
Classifier: Programming Language :: Python :: 3.13
Classifier: Programming Language :: Python :: 3.14
Requires-Dist: numpy (>=2.3.4,<3.0.0)
Requires-Dist: pandas (>=2.3.3,<3.0.0)
Requires-Dist: scikit-learn (>=1.7.2,<2.0.0)
